syscheck/__init__.py
syscheck/checker.py
syscheck/monitor.py
syscheck/web.py
syscheck/widgets.py
syscheck/static/wrench-gear.png
syscheck/static/css/bootstrap-cerulean.min.css
syscheck/static/css/bootstrap-cosmo.min.css
syscheck/static/css/bootstrap-cyborg.min.css
syscheck/static/css/bootstrap-darkly.min.css
syscheck/static/css/bootstrap-flatly.min.css
syscheck/static/css/bootstrap-journal.min.css
syscheck/static/css/bootstrap-lumen.min.css
syscheck/static/css/bootstrap-paper.min.css
syscheck/static/css/bootstrap-readable.min.css
syscheck/static/css/bootstrap-sandstone.min.css
syscheck/static/css/bootstrap-simplex.min.css
syscheck/static/css/bootstrap-slate.min.css
syscheck/static/css/bootstrap-spacelab.min.css
syscheck/static/css/bootstrap-superhero.min.css
syscheck/static/css/bootstrap-theme.min.css
syscheck/static/css/bootstrap-united.min.css
syscheck/static/css/bootstrap-yeti.min.css
syscheck/static/css/bootstrap.min.css
syscheck/static/css/syscheck.css
syscheck/static/fonts/glyphicons-halflings-regular.eot
syscheck/static/fonts/glyphicons-halflings-regular.svg
syscheck/static/fonts/glyphicons-halflings-regular.ttf
syscheck/static/fonts/glyphicons-halflings-regular.woff
syscheck/static/fonts/glyphicons-halflings-regular.woff2
syscheck/static/js/syscheck.js
syscheck/templates/index.html
syscheck/templates/module-category.html
syscheck-0.3.1.dist-info/DESCRIPTION.rst
syscheck-0.3.1.dist-info/METADATA
syscheck-0.3.1.dist-info/RECORD
syscheck-0.3.1.dist-info/WHEEL
syscheck-0.3.1.dist-info/metadata.json
syscheck-0.3.1.dist-info/top_level.txt
