Metadata-Version: 2.0
Name: syscheck
Version: 0.3.1
Summary: Check the status of various systems
Home-page: https://bitbucket.org/mivade/syscheck
Author: Michael V. DePalatis
Author-email: mike@depalatis.net
License: BSD
Platform: UNKNOWN
Classifier: Development Status :: 5 - Production/Stable
Classifier: Environment :: Web Environment
Classifier: License :: OSI Approved :: BSD License
Classifier: Operating System :: OS Independent
Classifier: Programming Language :: Python :: 2.7
Classifier: Programming Language :: Python :: 3.4
Classifier: Topic :: System :: Monitoring
Requires-Dist: six
Requires-Dist: tornado (>=4.2)
Requires-Dist: tornadose (>=0.3.0)
